ocr_files/__init__.py
ocr_files/ocr.py
kiwanocr-0.1.4.dist-info/LICENSE
kiwanocr-0.1.4.dist-info/METADATA
kiwanocr-0.1.4.dist-info/WHEEL
kiwanocr-0.1.4.dist-info/top_level.txt
kiwanocr-0.1.4.dist-info/RECORD
