Metadata-Version: 2.1
Name: kiwanocr
Version: 0.1.4
Summary: OCR single or multiple files
Home-page: https://github.com/pypa/sampleproject
Author: Sandeep Junnarkar
Author-email: sjnews@gmail.com
License: UNKNOWN
Project-URL: Bug Tracker, https://github.com/pypa/sampleproject/issues
Platform: UNKNOWN
Classifier: Programming Language :: Python :: 3
Classifier: License :: OSI Approved :: MIT License
Classifier: Operating System :: OS Independent
Requires-Python: >=3.6
License-File: LICENSE
